sitewinder/__init__.py
sitewinder/sitewinder.py
sitewinder-0.0.1.dist-info/licenses/LICENSE
sitewinder-0.0.1.dist-info/METADATA
sitewinder-0.0.1.dist-info/WHEEL
sitewinder-0.0.1.dist-info/top_level.txt
sitewinder-0.0.1.dist-info/RECORD
