Metadata-Version: 2.4
Name: sitewinder
Version: 0.0.1
Summary: Angular-like components in pure Python with PyScript + pyhtml5.
Requires-Python: >=3.11
License-File: LICENSE
Requires-Dist: pyhtml5
Dynamic: license-file
